CHANGELOG.rst
messagebus-0.15.2.dist-info/METADATA
messagebus-0.15.2.dist-info/WHEEL
messagebus-0.15.2.dist-info/entry_points.txt
messagebus-0.15.2.dist-info/licenses/LICENSE
messagebus/__init__.py
messagebus/adapters/__init__.py
messagebus/adapters/prometheus/__init__.py
messagebus/adapters/prometheus/metrics_store.py
messagebus/domain/model/__init__.py
messagebus/domain/model/ids.py
messagebus/domain/model/message.py
messagebus/domain/model/metadata.py
messagebus/domain/model/model.py
messagebus/domain/model/transaction.py
messagebus/ports/__init__.py
messagebus/ports/observability.py
messagebus/py.typed
messagebus/service/_async/dependency.py
messagebus/service/_async/eventstream.py
messagebus/service/_async/registry.py
messagebus/service/_async/repository.py
messagebus/service/_async/unit_of_work.py
messagebus/service/_sync/dependency.py
messagebus/service/_sync/eventstream.py
messagebus/service/_sync/registry.py
messagebus/service/_sync/repository.py
messagebus/service/_sync/unit_of_work.py
messagebus/service/eventstream.py
messagebus/typing.py
messagebus-0.15.2.dist-info/RECORD
